refellips/__init__.py
refellips/dataSE.py
refellips/dispersion.py
refellips/objectiveSE.py
refellips/reflect_modelSE.py
refellips/structureSE.py
refellips/version.py
refellips/__pycache__/version.cpython-310.pyc
refellips/materials/air.csv
refellips/materials/aluminium_oxide.csv
refellips/materials/dmso.csv
refellips/materials/gold.csv
refellips/materials/pnipam.csv
refellips/materials/polymer_diffuse.csv
refellips/materials/polystyrene.csv
refellips/materials/silica.csv
refellips/materials/silicon.csv
refellips/materials/void.csv
refellips/materials/water.csv
refellips/tests/15-1-1.dat
refellips/tests/19-1-1.dat
refellips/tests/Cauchynk_fromWVASE.txt
refellips/tests/GaussianMulti_fromCompleteEase.txt
refellips/tests/Gaussnk_fromCompleteEase.txt
refellips/tests/Lorentznk_fromWVASE.txt
refellips/tests/Sellmeiernk_fromCompleteEase.txt
refellips/tests/TaucLorentz_fromCompleteEase.txt
refellips/tests/TestData_bareSI.txt
refellips/tests/TestData_cauchy.txt
refellips/tests/TestSuite.ipynb
refellips/tests/WVASE_Gaussian_example_225nmFilm_Multi.txt
refellips/tests/WVASE_Gaussian_example_40nmFilm_MultiWavelength_MultiAngle.txt
refellips/tests/WVASE_Lorentz_example_100nmFilm_MultiWavelength.txt
refellips/tests/WVASE_Sellmeier_example_75nmFilm_MultiWavelength_MultiAngle.txt
refellips/tests/WVASE_TaucLorentz_example_350nmFilm_MultiWavelength_MultiAngle.txt
refellips/tests/WVASE_example_10nmSiO2_325nmAl2O3_MultiWavelength.txt
refellips/tests/WVASE_example_2nmSiO2_117nmAu_MultiWavelength.txt
refellips/tests/WVASE_example_2nmSiO2_20nmPNIPAM_50EMA_MultiWavelength.txt
refellips/tests/WVASE_example_2nmSiO2_20nmPNIPAM_MultiWavelength.txt
refellips/tests/WVASE_example_2nmSiO2_65nmAl2O3_MultiWavelength.txt
refellips/tests/WVASE_example_30nmSiO2_Water_MultiWavelength.txt
refellips/tests/WVASE_example_3nmSiO2_30EMA_MultiWavelength.txt
refellips/tests/WVASE_example_3nmSiO2_90nmPNIPAM_20EMA-MG_MultiWavelength.txt
refellips-0.0.5.dist-info/LICENSE
refellips-0.0.5.dist-info/METADATA
refellips-0.0.5.dist-info/WHEEL
refellips-0.0.5.dist-info/top_level.txt
refellips-0.0.5.dist-info/RECORD
